metasub_utils.athena-0.2.0-py3.6-nspkg.pth
metasub_utils/athena/__init__.py
metasub_utils/athena/cli.py
metasub_utils/athena/constants.py
metasub_utils.athena-0.2.0.dist-info/METADATA
metasub_utils.athena-0.2.0.dist-info/RECORD
metasub_utils.athena-0.2.0.dist-info/WHEEL
metasub_utils.athena-0.2.0.dist-info/namespace_packages.txt
metasub_utils.athena-0.2.0.dist-info/top_level.txt
